adams_shell_wear/__init__.py
adams_shell_wear/apply.py
adams_shell_wear/archard.py
adams_shell_wear/facets.py
adams_shell_wear/parallel_face_finder.py
adams_shell_wear/tmp.py
adams_shell_wear/visualize.py
adams_shell_wear/wearable_shell.py
adams_shell_wear/utils/__init__.py
adams_shell_wear/utils/cs.py
adams_shell_wear/utils/dereferencer.py
adams_shell_wear/utils/plane.py
adams_shell_wear/utils/shell_file.py
adams_shell_wear/utils/utils.py
adams_shell_wear-1.1.1.dist-info/LICENSE
adams_shell_wear-1.1.1.dist-info/METADATA
adams_shell_wear-1.1.1.dist-info/WHEEL
adams_shell_wear-1.1.1.dist-info/top_level.txt
adams_shell_wear-1.1.1.dist-info/RECORD
